calc_elastic_elate.py
elastic_constants.py
elastic_mechanical_properties.py
elastool_elate_browser.py
find_spg.py
material_analysis.py
read_parameters.py
read_struct.py
stability_criteria.py
mechviz-1.0.data/scripts/elastoollite
mechviz-1.0.data/scripts/mechviz
mechviz-1.0.dist-info/LICENSE
mechviz-1.0.dist-info/METADATA
mechviz-1.0.dist-info/WHEEL
mechviz-1.0.dist-info/top_level.txt
mechviz-1.0.dist-info/RECORD
