Metadata-Version: 2.1
Name: mechviz
Version: 1.0
Summary: MechViz -- Python-based toolkit for the analysis and visualization of mechanical properties of materials
Home-page: https://sourceforge.net/projects/mechviz/
Author: Chinedu Ekuma
Author-email: cekuma1@gmail.com
License: GNU GPL version 3
License-File: LICENSE
Requires-Dist: numpy
Requires-Dist: scipy
Requires-Dist: matplotlib
Requires-Dist: pandas
Requires-Dist: seaborn
Requires-Dist: pymatgen
Requires-Dist: kaleido
Requires-Dist: plotly
Requires-Dist: spglib
Requires-Dist: ase
Requires-Dist: pyvista
Requires-Dist: selenium
